[
    {
        "name": "Bernhard II, Duke of Saxe-Meiningen",
        "occupation": "POLITICIAN",
        "gender": "M",
        "birthYear": "1800",
        "birthPlaceName": "Meiningen",
        "birthPlaceCountry": "Germany",
        "deathYear": "1882",
        "deathPlaceName": "Meiningen",
        "deathPlaceCountry": "Germany"
    },
    {
        "name": "William Stewart Halsted",
        "occupation": "PHYSICIAN",
        "gender": "M",
        "birthYear": "1852",
        "birthPlaceName": "New York City",
        "birthPlaceCountry": "United States",
        "deathYear": "1922",
        "deathPlaceName": "Johns Hopkins Hospital",
        "deathPlaceCountry": "United States"
    },
    {
        "name": "John Casimir of the Palatinate-Simmern",
        "occupation": "NOBLEMAN",
        "gender": "M",
        "birthYear": "1543",
        "birthPlaceName": "Simmern",
        "birthPlaceCountry": "Germany",
        "deathYear": "1592",
        "deathPlaceName": "Heidelberg",
        "deathPlaceCountry": "Germany"
    },
    {
        "name": "Dean Rusk",
        "occupation": "POLITICIAN",
        "gender": "M",
        "birthYear": "1909",
        "birthPlaceName": "Cherokee County, Georgia",
        "birthPlaceCountry": "United States",
        "deathYear": "1994",
        "deathPlaceName": "Athens, Georgia",
        "deathPlaceCountry": "United States"
    },
    {
        "name": "Friedrich Melchior, Baron von Grimm",
        "occupation": "WRITER",
        "gender": "M",
        "birthYear": "1723",
        "birthPlaceName": "Regensburg",
        "birthPlaceCountry": "Germany",
        "deathYear": "1807",
        "deathPlaceName": "Gotha",
        "deathPlaceCountry": "Germany"
    },
    {
        "name": "Eudokia Ingerina",
        "occupation": "POLITICIAN",
        "gender": "F",
        "birthYear": "840",
        "birthPlaceName": "",
        "birthPlaceCountry": "",
        "deathYear": "882",
        "deathPlaceName": "Istanbul",
        "deathPlaceCountry": "Turkey"
    },
    {
        "name": "Robert Fisk",
        "occupation": "WRITER",
        "gender": "M",
        "birthYear": "1946",
        "birthPlaceName": "Maidstone",
        "birthPlaceCountry": "United Kingdom",
        "deathYear": "2020",
        "deathPlaceName": "Dublin",
        "deathPlaceCountry": "Ireland"
    },
    {
        "name": "Kylian Mbapp\u00e9",
        "occupation": "SOCCER PLAYER",
        "gender": "M",
        "birthYear": "1998",
        "birthPlaceName": "Paris",
        "birthPlaceCountry": "France",
        "deathYear": "",
        "deathPlaceName": "",
        "deathPlaceCountry": ""
    },
    {
        "name": "Archduchess Maria Theresa of Austria-Este",
        "occupation": "NOBLEMAN",
        "gender": "F",
        "birthYear": "1817",
        "birthPlaceName": "Modena",
        "birthPlaceCountry": "Italy",
        "deathYear": "1886",
        "deathPlaceName": "Gorizia",
        "deathPlaceCountry": "Italy"
    },
    {
        "name": "Henry Howard, Earl of Surrey",
        "occupation": "POLITICIAN",
        "gender": "M",
        "birthYear": "1516",
        "birthPlaceName": "Hunsdon",
        "birthPlaceCountry": "United Kingdom",
        "deathYear": "1547",
        "deathPlaceName": "Tower Hill",
        "deathPlaceCountry": "United Kingdom"
    },
    {
        "name": "Ahmet Ertegun",
        "occupation": "MUSICIAN",
        "gender": "M",
        "birthYear": "1923",
        "birthPlaceName": "Istanbul",
        "birthPlaceCountry": "Turkey",
        "deathYear": "2006",
        "deathPlaceName": "New York City",
        "deathPlaceCountry": "United States"
    },
    {
        "name": "Alison Steadman",
        "occupation": "ACTOR",
        "gender": "F",
        "birthYear": "1946",
        "birthPlaceName": "Liverpool",
        "birthPlaceCountry": "United Kingdom",
        "deathYear": "",
        "deathPlaceName": "",
        "deathPlaceCountry": ""
    },
    {
        "name": "Lazar Mojsov",
        "occupation": "POLITICIAN",
        "gender": "M",
        "birthYear": "1920",
        "birthPlaceName": "Negotino",
        "birthPlaceCountry": "North Macedonia",
        "deathYear": "2011",
        "deathPlaceName": "Belgrade",
        "deathPlaceCountry": "Serbia"
    },
    {
        "name": "Edward Waring",
        "occupation": "MATHEMATICIAN",
        "gender": "M",
        "birthYear": "1736",
        "birthPlaceName": "Shrewsbury",
        "birthPlaceCountry": "United Kingdom",
        "deathYear": "1798",
        "deathPlaceName": "Plealey",
        "deathPlaceCountry": "United Kingdom"
    },
    {
        "name": "Yohannes IV",
        "occupation": "POLITICIAN",
        "gender": "M",
        "birthYear": "1837",
        "birthPlaceName": "Degol Woyane",
        "birthPlaceCountry": "Ethiopia",
        "deathYear": "1889",
        "deathPlaceName": "Metemma",
        "deathPlaceCountry": "Ethiopia"
    },
    {
        "name": "Friedrich, Prince of Waldeck and Pyrmont",
        "occupation": "POLITICIAN",
        "gender": "M",
        "birthYear": "1865",
        "birthPlaceName": "Bad Arolsen",
        "birthPlaceCountry": "Germany",
        "deathYear": "1946",
        "deathPlaceName": "Bad Arolsen",
        "deathPlaceCountry": "Germany"
    },
    {
        "name": "Rita Marley",
        "occupation": "SINGER",
        "gender": "F",
        "birthYear": "1946",
        "birthPlaceName": "Santiago de Cuba",
        "birthPlaceCountry": "Cuba",
        "deathYear": "",
        "deathPlaceName": "",
        "deathPlaceCountry": ""
    },
    {
        "name": "Andoni Goikoetxea Olaskoaga",
        "occupation": "SOCCER PLAYER",
        "gender": "M",
        "birthYear": "1956",
        "birthPlaceName": "Alonsotegi",
        "birthPlaceCountry": "Spain",
        "deathYear": "",
        "deathPlaceName": "",
        "deathPlaceCountry": ""
    },
    {
        "name": "Francesco Algarotti",
        "occupation": "PHILOSOPHER",
        "gender": "M",
        "birthYear": "1712",
        "birthPlaceName": "Venice",
        "birthPlaceCountry": "Italy",
        "deathYear": "1764",
        "deathPlaceName": "Pisa",
        "deathPlaceCountry": "Italy"
    },
    {
        "name": "Phan B\u1ed9i Ch\u00e2u",
        "occupation": "WRITER",
        "gender": "M",
        "birthYear": "1867",
        "birthPlaceName": "Ngh\u1ec7 An Province",
        "birthPlaceCountry": "Vietnam",
        "deathYear": "1940",
        "deathPlaceName": "Hu\u1ebf",
        "deathPlaceCountry": "Vietnam"
    },
    {
        "name": "Oliver Lodge",
        "occupation": "INVENTOR",
        "gender": "M",
        "birthYear": "1851",
        "birthPlaceName": "Penkhull",
        "birthPlaceCountry": "United Kingdom",
        "deathYear": "1940",
        "deathPlaceName": "Wilsford, Wiltshire",
        "deathPlaceCountry": "United Kingdom"
    },
    {
        "name": "Ivan Regen",
        "occupation": "BIOLOGIST",
        "gender": "M",
        "birthYear": "1868",
        "birthPlaceName": "Gorenja Vas, Gorenja Vas\u2013Poljane",
        "birthPlaceCountry": "Slovenia",
        "deathYear": "1947",
        "deathPlaceName": "Vienna",
        "deathPlaceCountry": "Austria"
    },
    {
        "name": "Lady Katherine Grey",
        "occupation": "NOBLEMAN",
        "gender": "F",
        "birthYear": "1540",
        "birthPlaceName": "Bradgate Park",
        "birthPlaceCountry": "United Kingdom",
        "deathYear": "1568",
        "deathPlaceName": "Cockfield Hall",
        "deathPlaceCountry": "United Kingdom"
    },
    {
        "name": "Horst-Dieter H\u00f6ttges",
        "occupation": "SOCCER PLAYER",
        "gender": "M",
        "birthYear": "1943",
        "birthPlaceName": "M\u00f6nchengladbach",
        "birthPlaceCountry": "Germany",
        "deathYear": "",
        "deathPlaceName": "",
        "deathPlaceCountry": ""
    },
    {
        "name": "Javier Saviola",
        "occupation": "SOCCER PLAYER",
        "gender": "M",
        "birthYear": "1981",
        "birthPlaceName": "Buenos Aires",
        "birthPlaceCountry": "Argentina",
        "deathYear": "",
        "deathPlaceName": "",
        "deathPlaceCountry": ""
    },
    {
        "name": "Alfred Clebsch",
        "occupation": "MATHEMATICIAN",
        "gender": "M",
        "birthYear": "1833",
        "birthPlaceName": "K\u00f6nigsberg",
        "birthPlaceCountry": "Russia",
        "deathYear": "1872",
        "deathPlaceName": "G\u00f6ttingen",
        "deathPlaceCountry": "Germany"
    },
    {
        "name": "Niccol\u00f2 Antonio Zingarelli",
        "occupation": "COMPOSER",
        "gender": "M",
        "birthYear": "1752",
        "birthPlaceName": "Naples",
        "birthPlaceCountry": "Italy",
        "deathYear": "1837",
        "deathPlaceName": "Torre del Greco",
        "deathPlaceCountry": "Italy"
    },
    {
        "name": "Stanis\u0142aw Bu\u0142ak-Ba\u0142achowicz",
        "occupation": "MILITARY PERSONNEL",
        "gender": "M",
        "birthYear": "1883",
        "birthPlaceName": "Ignalina District Municipality",
        "birthPlaceCountry": "Lithuania",
        "deathYear": "1940",
        "deathPlaceName": "Warsaw",
        "deathPlaceCountry": "Poland"
    },
    {
        "name": "Vinnie Vincent",
        "occupation": "MUSICIAN",
        "gender": "M",
        "birthYear": "1952",
        "birthPlaceName": "Bridgeport, Connecticut",
        "birthPlaceCountry": "United States",
        "deathYear": "",
        "deathPlaceName": "",
        "deathPlaceCountry": ""
    },
    {
        "name": "Abd\u00fclkerim Nadir Pasha",
        "occupation": "MILITARY PERSONNEL",
        "gender": "F",
        "birthYear": "1807",
        "birthPlaceName": "Chirpan",
        "birthPlaceCountry": "Bulgaria",
        "deathYear": "1883",
        "deathPlaceName": "Rhodes",
        "deathPlaceCountry": "Greece"
    },
    {
        "name": "Petre Roman",
        "occupation": "POLITICIAN",
        "gender": "M",
        "birthYear": "1946",
        "birthPlaceName": "Bucharest",
        "birthPlaceCountry": "Romania",
        "deathYear": "",
        "deathPlaceName": "",
        "deathPlaceCountry": ""
    },
    {
        "name": "David Armstrong-Jones, 2nd Earl of Snowdon",
        "occupation": "POLITICIAN",
        "gender": "M",
        "birthYear": "1961",
        "birthPlaceName": "Clarence House",
        "birthPlaceCountry": "United Kingdom",
        "deathYear": "",
        "deathPlaceName": "",
        "deathPlaceCountry": ""
    },
    {
        "name": "Alberto Cavalcanti",
        "occupation": "FILM DIRECTOR",
        "gender": "M",
        "birthYear": "1897",
        "birthPlaceName": "Rio de Janeiro",
        "birthPlaceCountry": "Brazil",
        "deathYear": "1982",
        "deathPlaceName": "Paris",
        "deathPlaceCountry": "France"
    },
    {
        "name": "Melchor Cano",
        "occupation": "PHILOSOPHER",
        "gender": "M",
        "birthYear": "1509",
        "birthPlaceName": "Taranc\u00f3n",
        "birthPlaceCountry": "Spain",
        "deathYear": "1560",
        "deathPlaceName": "Toledo, Spain",
        "deathPlaceCountry": "Spain"
    },
    {
        "name": "Mel Blanc",
        "occupation": "ACTOR",
        "gender": "M",
        "birthYear": "1908",
        "birthPlaceName": "San Francisco",
        "birthPlaceCountry": "United States",
        "deathYear": "1989",
        "deathPlaceName": "Los Angeles",
        "deathPlaceCountry": "United States"
    },
    {
        "name": "Tasuku Honjo",
        "occupation": "PHYSICIAN",
        "gender": "M",
        "birthYear": "1942",
        "birthPlaceName": "Kyoto",
        "birthPlaceCountry": "Japan",
        "deathYear": "",
        "deathPlaceName": "",
        "deathPlaceCountry": ""
    },
    {
        "name": "Francisco de S\u00e1 Carneiro",
        "occupation": "POLITICIAN",
        "gender": "M",
        "birthYear": "1934",
        "birthPlaceName": "Porto",
        "birthPlaceCountry": "Portugal",
        "deathYear": "1980",
        "deathPlaceName": "Camarate",
        "deathPlaceCountry": "Portugal"
    },
    {
        "name": "Ross Perot",
        "occupation": "POLITICIAN",
        "gender": "M",
        "birthYear": "1930",
        "birthPlaceName": "Texarkana, Texas",
        "birthPlaceCountry": "United States",
        "deathYear": "2019",
        "deathPlaceName": "Dallas",
        "deathPlaceCountry": "United States"
    },
    {
        "name": "Liza Marklund",
        "occupation": "WRITER",
        "gender": "F",
        "birthYear": "1962",
        "birthPlaceName": "Pite\u00e5",
        "birthPlaceCountry": "Sweden",
        "deathYear": "",
        "deathPlaceName": "",
        "deathPlaceCountry": ""
    },
    {
        "name": "Qin Jiushao",
        "occupation": "MATHEMATICIAN",
        "gender": "M",
        "birthYear": "1201",
        "birthPlaceName": "Anyue County",
        "birthPlaceCountry": "China",
        "deathYear": "1261",
        "deathPlaceName": "Guangdong",
        "deathPlaceCountry": "China"
    },
    {
        "name": "Enzo Scifo",
        "occupation": "SOCCER PLAYER",
        "gender": "M",
        "birthYear": "1966",
        "birthPlaceName": "La Louvi\u00e8re",
        "birthPlaceCountry": "Belgium",
        "deathYear": "",
        "deathPlaceName": "",
        "deathPlaceCountry": ""
    },
    {
        "name": "Frederick, Duke of Bavaria",
        "occupation": "POLITICIAN",
        "gender": "M",
        "birthYear": "1339",
        "birthPlaceName": "",
        "birthPlaceCountry": "",
        "deathYear": "1393",
        "deathPlaceName": "\u010cesk\u00e9 Bud\u011bjovice",
        "deathPlaceCountry": "Czechia"
    },
    {
        "name": "Bohemond V of Antioch",
        "occupation": "POLITICIAN",
        "gender": "M",
        "birthYear": "1199",
        "birthPlaceName": "Principality of Antioch",
        "birthPlaceCountry": "Turkey",
        "deathYear": "1252",
        "deathPlaceName": "",
        "deathPlaceCountry": ""
    },
    {
        "name": "Max Erwin von Scheubner-Richter",
        "occupation": "POLITICIAN",
        "gender": "M",
        "birthYear": "1884",
        "birthPlaceName": "Riga",
        "birthPlaceCountry": "Latvia",
        "deathYear": "1923",
        "deathPlaceName": "Munich",
        "deathPlaceCountry": "Germany"
    },
    {
        "name": "Isabella of Valois, Duchess of Bourbon",
        "occupation": "POLITICIAN",
        "gender": "F",
        "birthYear": "1313",
        "birthPlaceName": "",
        "birthPlaceCountry": "",
        "deathYear": "1383",
        "deathPlaceName": "Paris",
        "deathPlaceCountry": "France"
    },
    {
        "name": "Eric Knight",
        "occupation": "WRITER",
        "gender": "M",
        "birthYear": "1897",
        "birthPlaceName": "Menston",
        "birthPlaceCountry": "United Kingdom",
        "deathYear": "1943",
        "deathPlaceName": "Suriname",
        "deathPlaceCountry": "Suriname"
    },
    {
        "name": "Pierre Cl\u00e9menti",
        "occupation": "ACTOR",
        "gender": "F",
        "birthYear": "1942",
        "birthPlaceName": "Paris",
        "birthPlaceCountry": "France",
        "deathYear": "1999",
        "deathPlaceName": "Paris",
        "deathPlaceCountry": "France"
    },
    {
        "name": "Oenopides",
        "occupation": "ASTRONOMER",
        "gender": "F",
        "birthYear": "-490",
        "birthPlaceName": "Chios",
        "birthPlaceCountry": "Greece",
        "deathYear": "-420",
        "deathPlaceName": "",
        "deathPlaceCountry": ""
    },
    {
        "name": "Coenus of Macedon",
        "occupation": "POLITICIAN",
        "gender": "M",
        "birthYear": "-900",
        "birthPlaceName": "",
        "birthPlaceCountry": "",
        "deathYear": "-800",
        "deathPlaceName": "",
        "deathPlaceCountry": ""
    },
    {
        "name": "Olga Baclanova",
        "occupation": "ACTOR",
        "gender": "F",
        "birthYear": "1893",
        "birthPlaceName": "Moscow",
        "birthPlaceCountry": "Russia",
        "deathYear": "1974",
        "deathPlaceName": "Vevey",
        "deathPlaceCountry": "Switzerland"
    },
    {
        "name": "Friedrich Traun",
        "occupation": "ATHLETE",
        "gender": "M",
        "birthYear": "1876",
        "birthPlaceName": "Wandsbek",
        "birthPlaceCountry": "Germany",
        "deathYear": "1908",
        "deathPlaceName": "Hamburg",
        "deathPlaceCountry": "Germany"
    },
    {
        "name": "Holden Roberto",
        "occupation": "POLITICIAN",
        "gender": "M",
        "birthYear": "1923",
        "birthPlaceName": "M'banza-Kongo",
        "birthPlaceCountry": "Angola",
        "deathYear": "2007",
        "deathPlaceName": "Luanda",
        "deathPlaceCountry": "Angola"
    },
    {
        "name": "David Blaine",
        "occupation": "MAGICIAN",
        "gender": "M",
        "birthYear": "1973",
        "birthPlaceName": "Brooklyn",
        "birthPlaceCountry": "United States",
        "deathYear": "",
        "deathPlaceName": "",
        "deathPlaceCountry": ""
    },
    {
        "name": "Liutgard of Saxony",
        "occupation": "COMPANION",
        "gender": "F",
        "birthYear": "845",
        "birthPlaceName": "",
        "birthPlaceCountry": "",
        "deathYear": "885",
        "deathPlaceName": "",
        "deathPlaceCountry": ""
    },
    {
        "name": "Euronymous",
        "occupation": "MUSICIAN",
        "gender": "M",
        "birthYear": "1968",
        "birthPlaceName": "Surnadal",
        "birthPlaceCountry": "Norway",
        "deathYear": "1993",
        "deathPlaceName": "Oslo",
        "deathPlaceCountry": "Norway"
    },
    {
        "name": "Ieronim Uborevich",
        "occupation": "MILITARY PERSONNEL",
        "gender": "M",
        "birthYear": "1896",
        "birthPlaceName": "Kovno Governorate",
        "birthPlaceCountry": "Lithuania",
        "deathYear": "1937",
        "deathPlaceName": "Moscow",
        "deathPlaceCountry": "Russia"
    },
    {
        "name": "Cartimandua",
        "occupation": "POLITICIAN",
        "gender": "F",
        "birthYear": "50",
        "birthPlaceName": "",
        "birthPlaceCountry": "",
        "deathYear": "69",
        "deathPlaceName": "Great Britain",
        "deathPlaceCountry": "United Kingdom"
    },
    {
        "name": "Jorge Mar\u00eda Mej\u00eda",
        "occupation": "RELIGIOUS FIGURE",
        "gender": "M",
        "birthYear": "1923",
        "birthPlaceName": "Buenos Aires",
        "birthPlaceCountry": "Argentina",
        "deathYear": "2014",
        "deathPlaceName": "Rome",
        "deathPlaceCountry": "Italy"
    },
    {
        "name": "Traicho Kostov",
        "occupation": "POLITICIAN",
        "gender": "M",
        "birthYear": "1897",
        "birthPlaceName": "Sofia",
        "birthPlaceCountry": "Bulgaria",
        "deathYear": "1949",
        "deathPlaceName": "Sofia",
        "deathPlaceCountry": "Bulgaria"
    },
    {
        "name": "Jimmy Smith",
        "occupation": "MUSICIAN",
        "gender": "M",
        "birthYear": "1925",
        "birthPlaceName": "Norristown, Pennsylvania",
        "birthPlaceCountry": "United States",
        "deathYear": "2005",
        "deathPlaceName": "Scottsdale, Arizona",
        "deathPlaceCountry": "United States"
    },
    {
        "name": "Karl Friedrich Burdach",
        "occupation": "PHYSICIAN",
        "gender": "M",
        "birthYear": "1776",
        "birthPlaceName": "Leipzig",
        "birthPlaceCountry": "Germany",
        "deathYear": "1847",
        "deathPlaceName": "K\u00f6nigsberg",
        "deathPlaceCountry": "Russia"
    },
    {
        "name": "Aleksander Chod\u017ako",
        "occupation": "WRITER",
        "gender": "M",
        "birthYear": "1804",
        "birthPlaceName": "Myadzyel District",
        "birthPlaceCountry": "Belarus",
        "deathYear": "1891",
        "deathPlaceName": "Noisy-le-Sec",
        "deathPlaceCountry": "France"
    },
    {
        "name": "Hu Hanmin",
        "occupation": "POLITICIAN",
        "gender": "F",
        "birthYear": "1879",
        "birthPlaceName": "Panyu District",
        "birthPlaceCountry": "China",
        "deathYear": "1936",
        "deathPlaceName": "Guangdong",
        "deathPlaceCountry": "China"
    },
    {
        "name": "Tim Rice",
        "occupation": "MUSICIAN",
        "gender": "M",
        "birthYear": "1944",
        "birthPlaceName": "Shardeloes",
        "birthPlaceCountry": "United Kingdom",
        "deathYear": "",
        "deathPlaceName": "",
        "deathPlaceCountry": ""
    },
    {
        "name": "Prince Ludwig August of Saxe-Coburg and Gotha",
        "occupation": "POLITICIAN",
        "gender": "M",
        "birthYear": "1845",
        "birthPlaceName": "Ch\u00e2teau d'Eu",
        "birthPlaceCountry": "France",
        "deathYear": "1907",
        "deathPlaceName": "Karlovy Vary",
        "deathPlaceCountry": "Czechia"
    },
    {
        "name": "Walther von L\u00fcttwitz",
        "occupation": "MILITARY PERSONNEL",
        "gender": "M",
        "birthYear": "1859",
        "birthPlaceName": "Bogacica, Opole Voivodeship",
        "birthPlaceCountry": "Poland",
        "deathYear": "1942",
        "deathPlaceName": "Wroc\u0142aw",
        "deathPlaceCountry": "Poland"
    },
    {
        "name": "Alexander Gomelsky",
        "occupation": "BASKETBALL PLAYER",
        "gender": "M",
        "birthYear": "1928",
        "birthPlaceName": "Kronstadt",
        "birthPlaceCountry": "Russia",
        "deathYear": "2005",
        "deathPlaceName": "Moscow",
        "deathPlaceCountry": "Russia"
    },
    {
        "name": "Asim Ferhatovi\u0107",
        "occupation": "SOCCER PLAYER",
        "gender": "M",
        "birthYear": "1933",
        "birthPlaceName": "Sarajevo",
        "birthPlaceCountry": "Bosnia and Herzegovina",
        "deathYear": "1987",
        "deathPlaceName": "Sarajevo",
        "deathPlaceCountry": "Bosnia and Herzegovina"
    },
    {
        "name": "Joseph Whitworth",
        "occupation": "INVENTOR",
        "gender": "M",
        "birthYear": "1803",
        "birthPlaceName": "Stockport",
        "birthPlaceCountry": "United Kingdom",
        "deathYear": "1887",
        "deathPlaceName": "Monte Carlo",
        "deathPlaceCountry": "Monaco"
    },
    {
        "name": "Roger Hanin",
        "occupation": "ACTOR",
        "gender": "M",
        "birthYear": "1925",
        "birthPlaceName": "Algiers",
        "birthPlaceCountry": "Algeria",
        "deathYear": "2015",
        "deathPlaceName": "Paris",
        "deathPlaceCountry": "France"
    },
    {
        "name": "David Coulthard",
        "occupation": "RACING DRIVER",
        "gender": "M",
        "birthYear": "1971",
        "birthPlaceName": "Twynholm",
        "birthPlaceCountry": "United Kingdom",
        "deathYear": "",
        "deathPlaceName": "",
        "deathPlaceCountry": ""
    },
    {
        "name": "Martino Martini",
        "occupation": "WRITER",
        "gender": "M",
        "birthYear": "1614",
        "birthPlaceName": "Trento",
        "birthPlaceCountry": "Italy",
        "deathYear": "1661",
        "deathPlaceName": "Hangzhou",
        "deathPlaceCountry": "China"
    },
    {
        "name": "Ab\u016b K\u0101mil Shuj\u0101\u02bf ibn Aslam",
        "occupation": "MATHEMATICIAN",
        "gender": "M",
        "birthYear": "850",
        "birthPlaceName": "Egypt",
        "birthPlaceCountry": "Egypt",
        "deathYear": "930",
        "deathPlaceName": "",
        "deathPlaceCountry": ""
    },
    {
        "name": "Franz M\u00fcntefering",
        "occupation": "POLITICIAN",
        "gender": "M",
        "birthYear": "1940",
        "birthPlaceName": "Arnsberg",
        "birthPlaceCountry": "Germany",
        "deathYear": "",
        "deathPlaceName": "",
        "deathPlaceCountry": ""
    },
    {
        "name": "Dyan Cannon",
        "occupation": "ACTOR",
        "gender": "F",
        "birthYear": "1937",
        "birthPlaceName": "Tacoma, Washington",
        "birthPlaceCountry": "United States",
        "deathYear": "",
        "deathPlaceName": "",
        "deathPlaceCountry": ""
    },
    {
        "name": "Miloslav Vlk",
        "occupation": "RELIGIOUS FIGURE",
        "gender": "M",
        "birthYear": "1932",
        "birthPlaceName": "Sepekov",
        "birthPlaceCountry": "Czechia",
        "deathYear": "2017",
        "deathPlaceName": "Prague",
        "deathPlaceCountry": "Czechia"
    },
    {
        "name": "Maria de Lourdes Pintasilgo",
        "occupation": "POLITICIAN",
        "gender": "F",
        "birthYear": "1930",
        "birthPlaceName": "Abrantes",
        "birthPlaceCountry": "Portugal",
        "deathYear": "2004",
        "deathPlaceName": "Lisbon",
        "deathPlaceCountry": "Portugal"
    },
    {
        "name": "Ted Levine",
        "occupation": "ACTOR",
        "gender": "M",
        "birthYear": "1957",
        "birthPlaceName": "Bellaire, Ohio",
        "birthPlaceCountry": "United States",
        "deathYear": "",
        "deathPlaceName": "",
        "deathPlaceCountry": ""
    },
    {
        "name": "Adelbert Schulz",
        "occupation": "MILITARY PERSONNEL",
        "gender": "M",
        "birthYear": "1903",
        "birthPlaceName": "Berlin",
        "birthPlaceCountry": "Germany",
        "deathYear": "1944",
        "deathPlaceName": "Shepetivka",
        "deathPlaceCountry": "Ukraine"
    },
    {
        "name": "Johann Ludwig Krebs",
        "occupation": "COMPOSER",
        "gender": "M",
        "birthYear": "1713",
        "birthPlaceName": "Buttelstedt",
        "birthPlaceCountry": "Germany",
        "deathYear": "1780",
        "deathPlaceName": "Altenburg",
        "deathPlaceCountry": "Germany"
    },
    {
        "name": "Patrick Magee",
        "occupation": "ACTOR",
        "gender": "M",
        "birthYear": "1922",
        "birthPlaceName": "Armagh",
        "birthPlaceCountry": "United Kingdom",
        "deathYear": "1982",
        "deathPlaceName": "Fulham",
        "deathPlaceCountry": "United Kingdom"
    },
    {
        "name": "Marcel Griaule",
        "occupation": "ANTHROPOLOGIST",
        "gender": "M",
        "birthYear": "1898",
        "birthPlaceName": "Aisy-sur-Arman\u00e7on",
        "birthPlaceCountry": "France",
        "deathYear": "1956",
        "deathPlaceName": "Paris",
        "deathPlaceCountry": "France"
    },
    {
        "name": "Hamza ibn-'Ali ibn-Ahmad",
        "occupation": "RELIGIOUS FIGURE",
        "gender": "M",
        "birthYear": "985",
        "birthPlaceName": "",
        "birthPlaceCountry": "",
        "deathYear": "1021",
        "deathPlaceName": "Mecca",
        "deathPlaceCountry": "Saudi Arabia"
    },
    {
        "name": "Jacob Schiff",
        "occupation": "POLITICIAN",
        "gender": "M",
        "birthYear": "1847",
        "birthPlaceName": "Frankfurt",
        "birthPlaceCountry": "Germany",
        "deathYear": "1920",
        "deathPlaceName": "Manhattan",
        "deathPlaceCountry": "United States"
    },
    {
        "name": "Nicholas Georgescu-Roegen",
        "occupation": "PHYSICIST",
        "gender": "M",
        "birthYear": "1906",
        "birthPlaceName": "Constan\u021ba",
        "birthPlaceCountry": "Romania",
        "deathYear": "1994",
        "deathPlaceName": "Nashville, Tennessee",
        "deathPlaceCountry": "United States"
    },
    {
        "name": "Alice of Champagne",
        "occupation": "COMPANION",
        "gender": "F",
        "birthYear": "1196",
        "birthPlaceName": "Jerusalem",
        "birthPlaceCountry": "Israel",
        "deathYear": "1246",
        "deathPlaceName": "Acre, Israel",
        "deathPlaceCountry": "Israel"
    },
    {
        "name": "Arda Turan",
        "occupation": "SOCCER PLAYER",
        "gender": "M",
        "birthYear": "1987",
        "birthPlaceName": "Fatih",
        "birthPlaceCountry": "Turkey",
        "deathYear": "",
        "deathPlaceName": "",
        "deathPlaceCountry": ""
    },
    {
        "name": "Louis I, Count of Nevers",
        "occupation": "NOBLEMAN",
        "gender": "M",
        "birthYear": "1272",
        "birthPlaceName": "",
        "birthPlaceCountry": "",
        "deathYear": "1322",
        "deathPlaceName": "Paris",
        "deathPlaceCountry": "France"
    },
    {
        "name": "Johann Schneider-Ammann",
        "occupation": "POLITICIAN",
        "gender": "M",
        "birthYear": "1952",
        "birthPlaceName": "Sumiswald",
        "birthPlaceCountry": "Switzerland",
        "deathYear": "",
        "deathPlaceName": "",
        "deathPlaceCountry": ""
    },
    {
        "name": "Johann Voldemar Jannsen",
        "occupation": "POLITICIAN",
        "gender": "M",
        "birthYear": "1819",
        "birthPlaceName": "Tartu",
        "birthPlaceCountry": "Estonia",
        "deathYear": "1890",
        "deathPlaceName": "Tartu",
        "deathPlaceCountry": "Estonia"
    },
    {
        "name": "Arvid Horn",
        "occupation": "POLITICIAN",
        "gender": "M",
        "birthYear": "1664",
        "birthPlaceName": "Halikko",
        "birthPlaceCountry": "Finland",
        "deathYear": "1742",
        "deathPlaceName": "Ekebyholm Castle",
        "deathPlaceCountry": "Sweden"
    },
    {
        "name": "Gabriele Veneziano",
        "occupation": "PHYSICIST",
        "gender": "M",
        "birthYear": "1942",
        "birthPlaceName": "Florence",
        "birthPlaceCountry": "Italy",
        "deathYear": "",
        "deathPlaceName": "",
        "deathPlaceCountry": ""
    },
    {
        "name": "Richard Parkes Bonington",
        "occupation": "PAINTER",
        "gender": "M",
        "birthYear": "1801",
        "birthPlaceName": "Arnold, Nottinghamshire",
        "birthPlaceCountry": "United Kingdom",
        "deathYear": "1828",
        "deathPlaceName": "London",
        "deathPlaceCountry": "United Kingdom"
    },
    {
        "name": "Justus Sustermans",
        "occupation": "PAINTER",
        "gender": "M",
        "birthYear": "1597",
        "birthPlaceName": "Antwerp",
        "birthPlaceCountry": "Belgium",
        "deathYear": "1681",
        "deathPlaceName": "Florence",
        "deathPlaceCountry": "Italy"
    },
    {
        "name": "Hans Tausen",
        "occupation": "RELIGIOUS FIGURE",
        "gender": "M",
        "birthYear": "1494",
        "birthPlaceName": "Birkende",
        "birthPlaceCountry": "Denmark",
        "deathYear": "1561",
        "deathPlaceName": "Ribe",
        "deathPlaceCountry": "Denmark"
    },
    {
        "name": "Alexander Bain",
        "occupation": "PSYCHOLOGIST",
        "gender": "M",
        "birthYear": "1818",
        "birthPlaceName": "Aberdeen",
        "birthPlaceCountry": "United Kingdom",
        "deathYear": "1903",
        "deathPlaceName": "Aberdeen",
        "deathPlaceCountry": "United Kingdom"
    },
    {
        "name": "King Xian of Zhou",
        "occupation": "POLITICIAN",
        "gender": "M",
        "birthYear": "-400",
        "birthPlaceName": "",
        "birthPlaceCountry": "",
        "deathYear": "-321",
        "deathPlaceName": "",
        "deathPlaceCountry": ""
    },
    {
        "name": "Archidamus V",
        "occupation": "POLITICIAN",
        "gender": "M",
        "birthYear": "-250",
        "birthPlaceName": "Sparta",
        "birthPlaceCountry": "Greece",
        "deathYear": "-220",
        "deathPlaceName": "Sparta",
        "deathPlaceCountry": "Greece"
    },
    {
        "name": "Pietro Lando",
        "occupation": "POLITICIAN",
        "gender": "M",
        "birthYear": "1462",
        "birthPlaceName": "Venice",
        "birthPlaceCountry": "Italy",
        "deathYear": "1545",
        "deathPlaceName": "Venice",
        "deathPlaceCountry": "Italy"
    },
    {
        "name": "Nicholas Aylward Vigors",
        "occupation": "POLITICIAN",
        "gender": "M",
        "birthYear": "1785",
        "birthPlaceName": "County Carlow",
        "birthPlaceCountry": "Ireland",
        "deathYear": "1840",
        "deathPlaceName": "London",
        "deathPlaceCountry": "United Kingdom"
    }
]